epycs/__init__.py
epycs/config.py
epycs/path.py
epycs/subprocess.py
epycs/tests/__init__.py
epycs/tests/test_subprocess.py
epycs-1.5.0.dist-info/licenses/LICENSE
epycs-1.5.0.dist-info/METADATA
epycs-1.5.0.dist-info/WHEEL
epycs-1.5.0.dist-info/top_level.txt
epycs-1.5.0.dist-info/RECORD
