Metadata-Version: 2.4
Name: epycs
Version: 1.5.0
Summary: Epycs is a simple way to convert shell scripts to python
Requires-Python: >=3.7
License-File: LICENSE
Dynamic: license-file
